pypotage/__init__.py
pypotage/shared.py
pypotage/utils.py
pypotage/abc/__init__.py
pypotage/abc/chefABC.py
pypotage/abc/chefLineABC.py
pypotage/abc/flavourABC.py
pypotage/abc/formula.py
pypotage/abc/ingredientABC.py
pypotage/abc/kitchenABC.py
pypotage/abc/mealABC.py
pypotage/abc/orderABC.py
pypotage/abc/potABC.py
pypotage/abc/waiterABC.py
pypotage/implementations/__init__.py
pypotage/implementations/chefLine.py
pypotage/implementations/fullyProxiedPackedMeal.py
pypotage/implementations/ingredient.py
pypotage/implementations/kitchen.py
pypotage/implementations/meal.py
pypotage/implementations/pot.py
pypotage/implementations/chefs/__init__.py
pypotage/implementations/chefs/cacheChef.py
pypotage/implementations/chefs/genericChef.py
pypotage/implementations/chefs/listChef.py
pypotage/implementations/flavours/__init__.py
pypotage/implementations/flavours/forcedTypeFlavour.py
pypotage/implementations/flavours/idFlavour.py
pypotage/implementations/flavours/lazyFlavour.py
pypotage/implementations/flavours/noCallFlavour.py
pypotage/implementations/flavours/orderFlavour.py
pypotage/implementations/flavours/primaryFlavour.py
pypotage/implementations/flavours/staticTypeCheckerFlavour.py
pypotage/implementations/flavours/typeFlavour.py
pypotage/implementations/orders/__init__.py
pypotage/implementations/orders/listOrder.py
pypotage/implementations/orders/order.py
pypotage/implementations/waiters/__init__.py
pypotage/implementations/waiters/cacheWaiter.py
pypotage/implementations/waiters/genericWaiter.py
pypotage/implementations/waiters/packedMealWaiter.py
pypotage/implementations/waiters/waiter.py
pypotage-2.0.0.1a0.dist-info/LICENSE
pypotage-2.0.0.1a0.dist-info/METADATA
pypotage-2.0.0.1a0.dist-info/WHEEL
pypotage-2.0.0.1a0.dist-info/top_level.txt
pypotage-2.0.0.1a0.dist-info/RECORD
