Metadata-Version: 2.1
Name: pypotage
Version: 2.0.0.1a0
Summary: A simple Python package that provides an easy way to use Dependency Injection in your projects.
Home-page: https://github.com/pavalso/potage
Author: Pavalso
License: MIT
Project-URL: Bug Tracker, https://github.com/pavalso/potage/issues
Classifier: Development Status :: 3 - Alpha
Classifier: Intended Audience :: Developers
Classifier: Natural Language :: English
Classifier: Programming Language :: Python :: 3.9
Classifier: Programming Language :: Python :: 3.10
Classifier: Programming Language :: Python :: 3.11
Classifier: Programming Language :: Python :: 3.12
Classifier: Topic :: Software Development :: Libraries
Classifier: Topic :: Software Development :: Libraries :: Python Modules
Classifier: License :: OSI Approved :: MIT License
Classifier: Operating System :: OS Independent
Classifier: Typing :: Typed
Requires-Python: >=3.9
License-File: LICENSE
Requires-Dist: typing_extensions==4.11.0
Requires-Dist: objproxies==0.9.4
Provides-Extra: dev
Requires-Dist: pytest==8.1.1; extra == "dev"
Requires-Dist: pytest-cov==5.0.0; extra == "dev"
Requires-Dist: Sphinx==7.3.7; extra == "dev"
Requires-Dist: sphinx_press_theme==0.9.1; extra == "dev"
Provides-Extra: test
Requires-Dist: pytest==8.1.1; extra == "test"
Requires-Dist: pytest-cov==5.0.0; extra == "test"
Provides-Extra: doc
Requires-Dist: Sphinx==7.3.7; extra == "doc"
Requires-Dist: sphinx_press_theme==0.9.1; extra == "doc"
